rivapy/__init__.py
rivapy/_converter.py
rivapy/config/__init__.py
rivapy/config/logging_config_manager.py
rivapy/config/logging_filters.py
rivapy/credit/__init__.py
rivapy/credit/creditmetrics.py
rivapy/instruments/__init__.py
rivapy/instruments/_logger.py
rivapy/instruments/bond_specifications.py
rivapy/instruments/cds_specification.py
rivapy/instruments/components.py
rivapy/instruments/deposit_specifications.py
rivapy/instruments/energy_futures_specifications.py
rivapy/instruments/factory.py
rivapy/instruments/fra_specifications.py
rivapy/instruments/gasstorage_specification.py
rivapy/instruments/ir_swap_specification.py
rivapy/instruments/ppa_specification.py
rivapy/instruments/specification_from_csv.py
rivapy/instruments/specifications.py
rivapy/marketdata/__init__.py
rivapy/marketdata/_logger.py
rivapy/marketdata/bootstrapping.py
rivapy/marketdata/curves.py
rivapy/marketdata/factory.py
rivapy/marketdata/fixing_table.py
rivapy/marketdata_tools/__init__.py
rivapy/marketdata_tools/factory.py
rivapy/marketdata_tools/pfc_shaper.py
rivapy/marketdata_tools/pfc_shifter.py
rivapy/models/__init__.py
rivapy/models/_logger.py
rivapy/models/base_model.py
rivapy/models/factory.py
rivapy/models/heston.py
rivapy/models/local_vol.py
rivapy/models/lucia_schwartz.py
rivapy/models/ornstein_uhlenbeck.py
rivapy/models/residual_demand_fwd_model.py
rivapy/models/residual_demand_model.py
rivapy/models/scott_chesney.py
rivapy/models/stoch_local_vol.py
rivapy/numerics/_logger.py
rivapy/numerics/kernel_regression.py
rivapy/pricing/__init__.py
rivapy/pricing/_logger.py
rivapy/pricing/analytics.py
rivapy/pricing/bond_pricing.py
rivapy/pricing/deep_hedging.py
rivapy/pricing/deposit_pricing.py
rivapy/pricing/factory.py
rivapy/pricing/fra_pricing.py
rivapy/pricing/gas_storage_pricer.py
rivapy/pricing/green_ppa_mean_pricer.py
rivapy/pricing/green_ppa_pricing.py
rivapy/pricing/interest_rate_swap_pricing.py
rivapy/pricing/pricer_old.py
rivapy/pricing/pricing_data.py
rivapy-1.0.0.dist-info/licenses/LICENSE
rivapy-1.0.0.dist-info/METADATA
rivapy-1.0.0.dist-info/WHEEL
rivapy-1.0.0.dist-info/top_level.txt
rivapy-1.0.0.dist-info/RECORD
