Metadata-Version: 2.4
Name: rivapy
Version: 1.0.0
Summary: RIVACON's Risk and Valuation Library
Author-email: RIVACON <info@rivacon.com>
Project-URL: Homepage, https://github.com/RIVACON/RiVaPy
Project-URL: Issues, https://github.com/RIVACON/RiVaPy/issues
Requires-Python: >=3.12
License-File: LICENSE
Requires-Dist: numpy
Requires-Dist: pandas
Requires-Dist: scikit-learn
Requires-Dist: scipy
Requires-Dist: openpyxl
Requires-Dist: python-dateutil
Requires-Dist: holidays
Requires-Dist: matplotlib
Dynamic: license-file
